AutomationSetup/__init__.py
AutomationSetup/bringUpSetup.py
bringUpSetup-1.0.2.dist-info/LICENSE.txt
bringUpSetup-1.0.2.dist-info/METADATA
bringUpSetup-1.0.2.dist-info/WHEEL
bringUpSetup-1.0.2.dist-info/top_level.txt
bringUpSetup-1.0.2.dist-info/RECORD
