Metadata-Version: 2.1
Name: bringUpSetup
Version: 1.0.2
Summary: This Package installs all the required packages for BringUp Automation Tool
Home-page: https://github.pie.apple.com/shree-kumar/BringUpAutomation/tree/SetUp
Author: ShreeKumar
Author-email: Shree Kumar <shree_kumar@apple.com>
Project-URL: Homepage, https://github.pie.apple.com/shree-kumar/BringUpAutomation/tree/SetUp
Classifier: Programming Language :: Python :: 3
Classifier: License :: OSI Approved :: MIT License
Classifier: Operating System :: MacOS
Requires-Python: >=3.8
License-File: LICENSE.txt
